parade/__init__.py
parade/command/feature/__init__.py
parade/command/feature/install.py
parade/command/feature/search.py
parade_feature-0.0.1.dist-info/DESCRIPTION.rst
parade_feature-0.0.1.dist-info/METADATA
parade_feature-0.0.1.dist-info/RECORD
parade_feature-0.0.1.dist-info/WHEEL
parade_feature-0.0.1.dist-info/metadata.json
parade_feature-0.0.1.dist-info/top_level.txt
