Metadata-Version: 2.0
Name: parade-feature
Version: 0.0.1
Summary: A feature module of parade
Home-page: https://github.com/bailaohe/parade-feature
Author: He Bai
Author-email: bailaohe@gmail.com
License: UNKNOWN
Keywords: parade,feature
Platform: any
Classifier: Development Status :: 4 - Beta
Classifier: Intended Audience :: Developers
Classifier: License :: OSI Approved :: Apache Software License
Classifier: Programming Language :: Python :: 3
Classifier: Topic :: Database
Classifier: Topic :: Software Development :: Libraries :: Python Modules
Classifier: Operating System :: Unix
Classifier: Operating System :: MacOS :: MacOS X
Classifier: Operating System :: Microsoft :: Windows
Classifier: Operating System :: POSIX
Requires-Python: >=3.4
Requires-Dist: PyGithub
Requires-Dist: parade
